arkcloud/__init__.py
arkcloud/ai/__init__.py
arkcloud/ai/detect.py
arkcloud/ai/ocr.py
arkcloud/ark/__init__.py
arkcloud/ark/admin.py
arkcloud/gamepad/__init__.py
arkcloud/gamepad/browser/__init__.py
arkcloud/gamepad/browser/xbox.py
arkcloud/gamepad/components/__init__.py
arkcloud/gamepad/components/base.py
arkcloud/gamepad/components/buttons.py
arkcloud/gamepad/components/directional_pad.py
arkcloud/gamepad/components/event.py
arkcloud/gamepad/components/joystick.py
arkcloud/gamepad/components/menu.py
arkcloud/gamepad/components/shoulder.py
arkcloud/gamepad/linux/__init__.py
arkcloud/gamepad/linux/example_1.py
arkcloud/lib/__init__.py
arkcloud/lib/configuration.py
arkcloud/lib/timer.py
arkcloud/web/__init__.py
arkcloud/web/driver/__init__.py
arkcloud/web/driver/driver.py
arkcloud/web/driver/chrome/__init__.py
arkcloud/web/driver/chrome/chrome.py
arkcloud/web/driver/chrome/options.py
arkcloud/web/driver/chrome/service.py
arkcloud/web/driver/components/__init__.py
arkcloud/web/driver/components/element.py
arkcloud/web/websites/__init__.py
arkcloud/web/websites/ark_website.py
arkcloud/web/websites/gamepad_website.py
arkcloud/web/websites/website.py
arkcloud/web/websites/xbox_controller_extension.py
arkcloud-0.0.21.dist-info/LICENSE
arkcloud-0.0.21.dist-info/METADATA
arkcloud-0.0.21.dist-info/WHEEL
arkcloud-0.0.21.dist-info/top_level.txt
arkcloud-0.0.21.dist-info/RECORD
