Metadata-Version: 2.1
Name: arkcloud
Version: 0.0.21
Summary: This application accesses the Ark system.
Home-page: https://github.com/GameServerGurus/Ark-Cloud
Author: Mauricio
Author-email: dev.mauricio.lomeli@gmail.com
Project-URL: Bug Tracker, https://github.com/GameServerGurus/Ark-Cloud/issues
Platform: win32
Classifier: Programming Language :: Python :: 3.9
Classifier: Programming Language :: Python :: 3.10
Classifier: License :: OSI Approved :: MIT License
Classifier: Operating System :: OS Independent
Requires-Python: >=3.9
License-File: LICENSE
Requires-Dist: arklibrary (==1.*)
Requires-Dist: requests (==2.*)
Requires-Dist: pytest (==7.*)
Requires-Dist: selenium (==4.*)
Requires-Dist: pytesseract (==0.*)
Requires-Dist: Pillow (==9.*)
Requires-Dist: beautifulsoup4 (==4.*)
Requires-Dist: opencv-python (==4.*)
Requires-Dist: numpy (==1.*)
Provides-Extra: testing
Requires-Dist: pytest (==7.*) ; extra == 'testing'
Requires-Dist: pytest-cov (>=2.0) ; extra == 'testing'
Requires-Dist: mypy (>=0.971) ; extra == 'testing'
Requires-Dist: flake8 (>=3.8) ; extra == 'testing'
Requires-Dist: tox (>=3.24) ; extra == 'testing'
